<idea-plugin>
  <extensionPoints>
    <extensionPoint name="moduleExtension" interface="com.intellij.openapi.roots.ModuleExtension" area="IDEA_MODULE" dynamic="true"/>
    <extensionPoint name="orderEnumerationHandlerFactory" interface="com.intellij.openapi.roots.OrderEnumerationHandler$Factory" dynamic="true"/>
    <extensionPoint name="filePropertyPusher" interface="com.intellij.openapi.roots.impl.FilePropertyPusher" dynamic="true"/>
    <extensionPoint name="projectFileScanner" interface="com.intellij.openapi.roots.impl.ProjectFileScanner" dynamic="true"/>
    <extensionPoint name="customLibraryTable" interface="com.intellij.openapi.roots.libraries.CustomLibraryTableDescription" dynamic="true"/>
    <extensionPoint name="orderRootType" interface="com.intellij.openapi.roots.OrderRootType"/>
  </extensionPoints>
</idea-plugin>
